bip85_cli.py
bip85lib/__init__.py
bip85lib/bip85.py
bip85_cli-0.0.2.dist-info/LICENSE
bip85_cli-0.0.2.dist-info/METADATA
bip85_cli-0.0.2.dist-info/WHEEL
bip85_cli-0.0.2.dist-info/entry_points.txt
bip85_cli-0.0.2.dist-info/top_level.txt
bip85_cli-0.0.2.dist-info/RECORD
