Metadata-Version: 2.1
Name: bip85-cli
Version: 0.0.2
Summary: Bip85 lib and cli written in python able to derive mnemonics from your master mnemonic.
Home-page: https://github.com/valerio-vaccaro/bip85-utils
Author: Valerio Vaccaro
Author-email: valerio.vaccaro@gmail.com
License: MIT
Classifier: Programming Language :: Python :: 3.7
Classifier: Operating System :: OS Independent
Requires-Python: >=3.7
License-File: LICENSE
Requires-Dist: colorama (==0.4.6)
Requires-Dist: termcolor (==2.4.0)
Requires-Dist: wallycore (==1.2.0)
